domipy/__init__.py
domipy/command.py
domipy/controller.py
domipy/message.py
domipy/module.py
domipy/module_directory.py
domipy/parser.py
domipy/connections/__init__.py
domipy/messages/__init__.py
domipy/messages/ai_status.py
domipy/messages/ao_status.py
domipy/messages/appinfo_request.py
domipy/messages/control.py
domipy/messages/dbir_status.py
domipy/messages/ddim_status.py
domipy/messages/di_status.py
domipy/messages/din10v_status.py
domipy/messages/dio_status.py
domipy/messages/dism_status.py
domipy/messages/dled_status.py
domipy/messages/dmov_status.py
domipy/messages/dmr_status.py
domipy/messages/do_status.py
domipy/messages/dpbu_status.py
domipy/messages/dtrp_status.py
domipy/messages/dtrv_status.py
domipy/messages/dtsc_status.py
domipy/messages/hello.py
domipy/messages/info.py
domipy/messages/login_request.py
domipy/messages/login_request_salt.py
domipy/messages/module_info.py
domipy/messages/module_status_request.py
domipy/messages/ping.py
domipy/messages/session_closed.py
domipy/messages/session_opened.py
domipy/messages/session_timeout.py
domipy/messages/set_ao.py
domipy/messages/set_di.py
domipy/messages/set_dimmer.py
domipy/messages/set_do.py
domipy/messages/set_temperature.py
domipy/messages/set_var.py
domipy/messages/temperature_status.py
domipy/messages/user_disconnected.py
domipy/messages/var_status.py
domipy/messages/waiting_for_loginsw.py
domipy/modules/__init__.py
domipy/modules/ddim01.py
domipy/modules/dism0x.py
domipy/modules/do.py
domipy/modules/dpbu0x.py
domipy/modules/dtemp.py
domipy/utils/__init__.py
domipy/utils/encoders.py
domipy-0.1.5.dist-info/LICENSE
domipy-0.1.5.dist-info/METADATA
domipy-0.1.5.dist-info/WHEEL
domipy-0.1.5.dist-info/top_level.txt
domipy-0.1.5.dist-info/RECORD
