Metadata-Version: 2.1
Name: domipy
Version: 0.1.5
Summary: A port of the python Library for the Domintell protocol using Secure Web Sockets and new login mecanism. Original work from Zilvinas Binisevicius (zilvinas@binis.me)
Home-page: https://github.com/soliveira/python-domintell
Author: Sérgio Oliveira
Author-email: so@soliveira.pt
License: MIT
Platform: any
License-File: LICENSE
Requires-Dist: pyserial
Requires-Dist: websocket-client
